ibase/SignGen.py
ibase/__init__.py
ibase/async_run.py
ibase/base.py
ibase/generate_script.py
ibase-0.0.2.dist-info/LICENSE
ibase-0.0.2.dist-info/METADATA
ibase-0.0.2.dist-info/WHEEL
ibase-0.0.2.dist-info/top_level.txt
ibase-0.0.2.dist-info/RECORD
