Metadata-Version: 2.1
Name: ibase
Version: 0.0.2
Summary: interface testcase script basefunc
Home-page: https://github.com/yangeren/ibase
Author: Hanz
Author-email: wanghan0406@autohome.com.cn
License: UNKNOWN
Platform: UNKNOWN
Classifier: Programming Language :: Python :: 3
Classifier: License :: OSI Approved :: MIT License
Classifier: Operating System :: OS Independent
Requires-Dist: requests
